thinkfic_downloader/__init__.py
thinkfic_downloader/config.py
thinkfic_downloader/logs.py
thinkfic_downloader/slides/__init__.py
thinkfic_downloader/slides/cli.py
thinkfic_downloader/slides/core.py
thinkfic_downloader/video/__init__.py
thinkfic_downloader/video/cli.py
thinkfic_downloader/video/core.py
thinkfic_downloader-0.1.1.dist-info/licenses/LICENSE
thinkfic_downloader-0.1.1.dist-info/METADATA
thinkfic_downloader-0.1.1.dist-info/WHEEL
thinkfic_downloader-0.1.1.dist-info/entry_points.txt
thinkfic_downloader-0.1.1.dist-info/top_level.txt
thinkfic_downloader-0.1.1.dist-info/RECORD
