Metadata-Version: 2.4
Name: thinkfic-downloader
Version: 0.1.1
Summary: Tools to download videos and slides from Thinkific
Author: Cervantes Hernandez
License-Expression: MIT
Project-URL: Homepage, https://github.com/crh2302/thinkfic-downloader
Project-URL: Repository, https://github.com/crh2302/thinkfic-downloader
Project-URL: Issues, https://github.com/crh2302/thinkfic-downloader/issues
Keywords: thinkific,downloader,videos,slides,yt-dlp
Requires-Python: >=3.9
License-File: LICENSE
Requires-Dist: pyyaml>=6.0
Requires-Dist: yt-dlp>=2025.1.15
Requires-Dist: requests>=2.32.0
Requires-Dist: pillow>=10.0.0
Requires-Dist: colorama>=0.4.6
Requires-Dist: tqdm>=4.66.0
Provides-Extra: dev
Requires-Dist: black>=24.0.0; extra == "dev"
Requires-Dist: flake8>=7.0.0; extra == "dev"
Requires-Dist: pytest>=8.0.0; extra == "dev"
Dynamic: license-file
